{
    "welcome_dialog_title": "Welcome to Advancing Library Visibility in Africa Project",
    "ok": "OK",
    "cancel": "Cancel",
    "save": "Save",
    "next": "Next",
    "submit_info": "Submit Info",
    "view_details": "View Details",
    "details": "Details",
    "images": "Images",
    "personal_information": "Personal Information",
    "activity_logs": "Activity logs",
    "no_data": "No data avaialable",
    "select_preferred_language": "Select your preferred language",
    "search_for_a_library": "Search for a library",
    "name_of_library": "Name of Library",
    "country": "Country",
    "type_of_library": "Type of library",
    "other_library_type": "Other Library Type",
    "street_address": "Street Address",
    "name_of_community_or_town": "Name of community or town",
    "library_contact_name": "Library Contact Name",
    "email_address_of_library_contact": "Email of library contact",
    "latitude": "Latitude",
    "longitude": "Longitude",
    "settings": "Settings",
    "help": "Help",
    "sign_out": "Sign out",
    "map": "Map",
    "libraries": "Libraries",
    "my_submissions": "My Submissions",
    "search_library": "Search for a library",
    "charts": "Charts",
    "search": "Search",
    "import_export": "Import / Export",
    "coordinates": "Coordinates",
    "attach_library_photo": "Attach a photo of the library",
    "progress_of_collection": "Progress of collection",
    "total_number_of_libraries": "Total number of libraries",
    "total_libraries_by_country": "Total number of libraries by country",
    "total_of_each_library_type_in_country": "Total number of each library type in a country",
    "total_of_approved_libraries_in_country": "Total number of approved libraries in a country",
    "all": "All",
    "approved": "Approved",
    "rejected": "Rejected",
    "pending_approval": "Pending Approval",
    "estimated_total": "Estimated total",
    "type": "Type",
    "filter_by_country": "Filter by country",
    "filter_by_type": "Filter by type",
    "download": "Download",
    "print": "Print"
}